jcl_parser/__init__.py
jcl_parser/cli.py
jcl_parser/interface.py
jcl_parser/jcl_parser.py
jcl_parser/logger.py
jcl_parser/extensions/__init__.py
jcl_parser/extensions/example_extension.py
jcl_parser/extractors/__init__.py
jcl_parser/extractors/base_extractor.py
jcl_parser/extractors/comment_extractor.py
jcl_parser/extractors/job_extractor.py
jcl_parser/extractors/proc_extractor.py
jcl_parser/extractors/step_extractor.py
legacylens_jcl_parser-0.1.9.dist-info/licenses/LICENSE
legacylens_jcl_parser-0.1.9.dist-info/METADATA
legacylens_jcl_parser-0.1.9.dist-info/WHEEL
legacylens_jcl_parser-0.1.9.dist-info/top_level.txt
legacylens_jcl_parser-0.1.9.dist-info/RECORD
