Metadata-Version: 2.4
Name: legacylens_jcl_parser
Version: 0.1.9
Summary: A parser for JCL (Job Control Language) files with JSON output
Author-email: Samuel Dion <sam94dion@gmail.com>
License: MIT
Project-URL: Homepage, https://github.com/sam94dion/legacylens-jcl-parser
Project-URL: Bug Tracker, https://github.com/sam94dion/legacylens-jcl-parser/issues
Classifier: Development Status :: 3 - Alpha
Classifier: Intended Audience :: Developers
Classifier: Programming Language :: Python :: 3
Classifier: Programming Language :: Python :: 3.6
Classifier: Programming Language :: Python :: 3.7
Classifier: Programming Language :: Python :: 3.8
Classifier: Programming Language :: Python :: 3.9
Classifier: Programming Language :: Python :: 3.10
Classifier: Programming Language :: Python :: 3.11
Classifier: License :: OSI Approved :: MIT License
Classifier: Operating System :: OS Independent
Requires-Python: >=3.7
License-File: LICENSE
Requires-Dist: typing-extensions>=3.7.4
Provides-Extra: dev
Requires-Dist: pytest>=6.0.0; extra == "dev"
Requires-Dist: pytest-cov>=2.10.0; extra == "dev"
Requires-Dist: black>=20.8b1; extra == "dev"
Requires-Dist: flake8>=3.8.0; extra == "dev"
Dynamic: license-file
